tidyhome/__init__.py
tidyhome/lookup.py
tidyhome/tidyhome.py
tidyhome/tests/__init__.py
tidyhome/tests/test_tidyhome.py
tidyhome-1.0.1.dist-info/LICENSE
tidyhome-1.0.1.dist-info/METADATA
tidyhome-1.0.1.dist-info/WHEEL
tidyhome-1.0.1.dist-info/top_level.txt
tidyhome-1.0.1.dist-info/RECORD
