Metadata-Version: 2.1
Name: tidyhome
Version: 1.0.1
Summary: Package for accessing CFPB U.S. home mortgage data
Home-page: https://github.com/summitllc/tidyhome-py
Author: Summit Consulting LLC
Author-email: 
License: UNKNOWN
Project-URL: Bug Tracker, https://github.com/summitllc/tidyhome-py/issues
Platform: UNKNOWN
Classifier: Programming Language :: Python :: 3
Classifier: License :: OSI Approved :: MIT License
Classifier: Operating System :: OS Independent
Requires-Python: >=3.6
License-File: LICENSE
Requires-Dist: pandas
Requires-Dist: requests
